LICENSE
MANIFEST.in
README
setup.py
conda.recipe/bld.bat
conda.recipe/build.sh
conda.recipe/meta.yaml
data/marker_112259237.png
data/marker_221052793.png
data/marker_44616414.png
roboticia_uno/__init__.py
roboticia_uno/_version.py
roboticia_uno/roboticia_uno.py
roboticia_uno/roboticia_uno.urdf
roboticia_uno.egg-info/PKG-INFO
roboticia_uno.egg-info/SOURCES.txt
roboticia_uno.egg-info/dependency_links.txt
roboticia_uno.egg-info/not-zip-safe
roboticia_uno.egg-info/requires.txt
roboticia_uno.egg-info/top_level.txt
roboticia_uno/configuration/roboticia_uno.json
roboticia_uno/primitives/__init__.py
roboticia_uno/primitives/dance.py
roboticia_uno/primitives/face_tracking.py
roboticia_uno/primitives/headfollow.py
roboticia_uno/primitives/jump.py
roboticia_uno/primitives/postures.py
roboticia_uno/primitives/tracking_feedback.py
roboticia_uno/vrep-scene/roboticia_uno.ttt
roboticia_uno/vrep-scene/roboticia_uno_empty.ttt
roboticia_uno/vrep-scene/roboticia_uno_holder.ttt
roboticia_uno/vrep-scene/timer.lua
samples/handsoff_demo.py
samples/marker_demo.py
samples/testbed.py
samples/img/motors.png
samples/notebooks/Discover your Poppy Ergo Jr.ipynb
samples/notebooks/Record, Save and Play Moves on Poppy Ergo Jr.ipynb