Metadata-Version: 1.0
Name: roboticia-uno
Version: 2.0.2
Summary: Roboticia-first Software Library
Home-page: https://github.com/Roboticia/Roboticia-first
Author: Julien JEHL
Author-email: julien.jehl@roboticia.com
License: GNU GENERAL PUBLIC LICENSE Version 3
Platform: UNKNOWN
